edwh_locust_plugin/__about__.py
edwh_locust_plugin/__init__.py
edwh_locust_plugin/locust_plugin.py
edwh_locust_plugin-0.1.2.dist-info/METADATA
edwh_locust_plugin-0.1.2.dist-info/WHEEL
edwh_locust_plugin-0.1.2.dist-info/entry_points.txt
edwh_locust_plugin-0.1.2.dist-info/licenses/LICENSE.txt
edwh_locust_plugin-0.1.2.dist-info/RECORD
